sqloquent/__init__.py
sqloquent/classes.py
sqloquent/errors.py
sqloquent/interfaces.py
sqloquent/migration.py
sqloquent/relations.py
sqloquent/tools.py
sqloquent/asyncql/__init__.py
sqloquent/asyncql/classes.py
sqloquent/asyncql/interfaces.py
sqloquent/asyncql/relations.py
sqloquent-0.7.0.dist-info/METADATA
sqloquent-0.7.0.dist-info/WHEEL
sqloquent-0.7.0.dist-info/entry_points.txt
sqloquent-0.7.0.dist-info/RECORD
