Metadata-Version: 2.4
Name: sqloquent
Version: 0.7.0
Summary: SQL/ORM library with included bindings for sqlite. Inspired by Laravel and in particular Eloquent, but built with a distributed use case in mind (e.g. Merkle DAGs).
Project-URL: Homepage, https://github.com/k98kurz/sqloquent
Project-URL: Bug Tracker, https://github.com/k98kurz/sqloquent/issues
Author-email: k98kurz <k98kurz@gmail.com>
License: Copyright (c) 2025 Jonathan Voss (k98kurz)
Classifier: Development Status :: 4 - Beta
Classifier: License :: OSI Approved :: ISC License (ISCL)
Classifier: Operating System :: OS Independent
Classifier: Programming Language :: Python :: 3
Classifier: Topic :: Database :: Front-Ends
Requires-Python: >=3.10
Requires-Dist: packify>=0.2.3
Provides-Extra: asyncql
Requires-Dist: aiosqlite>=0.19.0; extra == 'asyncql'
Requires-Dist: nest-asyncio==1.6.0; extra == 'asyncql'
